PyTestReport-0.2.1.data/data/capture.js
PyTestReport-0.2.1.data/data/default.css
PyTestReport-0.2.1.data/data/default.html
PyTestReport-0.2.1.data/data/default.js
PyTestReport-0.2.1.data/data/legency.css
PyTestReport-0.2.1.data/data/legency.html
PyTestReport-0.2.1.data/data/legency.js
pytestreport/HTMLTestRunner.py
pytestreport/PyTestReportPlug.py
pytestreport/SendEmail.py
pytestreport/__init__.py
pytestreport/api.py
pytestreport/static/css/default.css
pytestreport/static/css/legency.css
pytestreport/static/js/capture.js
pytestreport/static/js/default.js
pytestreport/static/js/legency.js
pytestreport/templates/default.html
pytestreport/templates/legency.html
PyTestReport-0.2.1.dist-info/LICENSE
PyTestReport-0.2.1.dist-info/METADATA
PyTestReport-0.2.1.dist-info/WHEEL
PyTestReport-0.2.1.dist-info/entry_points.txt
PyTestReport-0.2.1.dist-info/top_level.txt
PyTestReport-0.2.1.dist-info/RECORD
